setup.cfg
setup.py
image2text/__init__.py
image2text/statement.py
image2text/word.py
image2text.egg-info/PKG-INFO
image2text.egg-info/SOURCES.txt
image2text.egg-info/dependency_links.txt
image2text.egg-info/not-zip-safe
image2text.egg-info/requires.txt
image2text.egg-info/top_level.txt
image2text/analysis/__init__.py
image2text/analysis/general.py
image2text/analysis/statement.py
image2text/analysis/word.py
image2text/util/__init__.py
image2text/util/image.py
image2text/util/plt.py
image2text/util/train.py