Metadata-Version: 1.0
Name: image2text
Version: 0.1.1
Summary: Change kor, eng document image to text
Home-page: UNKNOWN
Author: nonameP
Author-email: nonamep765@gmail.com
License: MIT
Platform: UNKNOWN
